{
  "spacing-none": {
    "$type": "number",
    "$value": 0,
    "$extensions": {
      "com.figma.variableId": "VariableID:6298:45384",
      "com.figma.scopes": [
        "GAP"
      ],
      "com.figma.aliasData": {
        "targetVariableId": "VariableID:9a68fba684d65cc05c99cbd332cd4d4d8e720604/-1:-1",
        "targetVariableName": "Spacing/0 (0px)",
        "targetVariableSetId": "VariableCollectionId:fc3c86d2404c990c1ac80ea6da19380c4b1f10cc/-1:-1",
        "targetVariableSetName": "_Primitives"
      },
      "com.figma.isOverride": true
    }
  },
  "spacing-xxs": {
    "$type": "number",
    "$value": 2,
    "$extensions": {
      "com.figma.variableId": "VariableID:6298:45385",
      "com.figma.scopes": [
        "GAP"
      ],
      "com.figma.aliasData": {
        "targetVariableId": "VariableID:5ff5acd8892bd0ab9bc55341a8f326fda8bb00be/-1:-1",
        "targetVariableName": "Spacing/0․5 (2px)",
        "targetVariableSetId": "VariableCollectionId:fc3c86d2404c990c1ac80ea6da19380c4b1f10cc/-1:-1",
        "targetVariableSetName": "_Primitives"
      },
      "com.figma.isOverride": true
    }
  },
  "spacing-xs": {
    "$type": "number",
    "$value": 4,
    "$extensions": {
      "com.figma.variableId": "VariableID:6298:45386",
      "com.figma.scopes": [
        "GAP"
      ],
      "com.figma.aliasData": {
        "targetVariableId": "VariableID:ab6eaf3854eb447b7353dfe1aa48026e4f145a7a/-1:-1",
        "targetVariableName": "Spacing/1 (4px)",
        "targetVariableSetId": "VariableCollectionId:fc3c86d2404c990c1ac80ea6da19380c4b1f10cc/-1:-1",
        "targetVariableSetName": "_Primitives"
      },
      "com.figma.isOverride": true
    }
  },
  "spacing-sm": {
    "$type": "number",
    "$value": 6,
    "$extensions": {
      "com.figma.variableId": "VariableID:6425:327765",
      "com.figma.scopes": [
        "GAP"
      ],
      "com.figma.aliasData": {
        "targetVariableId": "VariableID:012c63702b43695b4b35a5045054307ef597d1d6/-1:-1",
        "targetVariableName": "Spacing/1․5 (6px)",
        "targetVariableSetId": "VariableCollectionId:fc3c86d2404c990c1ac80ea6da19380c4b1f10cc/-1:-1",
        "targetVariableSetName": "_Primitives"
      },
      "com.figma.isOverride": true
    }
  },
  "spacing-md": {
    "$type": "number",
    "$value": 8,
    "$extensions": {
      "com.figma.variableId": "VariableID:6298:45387",
      "com.figma.scopes": [
        "GAP"
      ],
      "com.figma.aliasData": {
        "targetVariableId": "VariableID:ffd4964d1391b6e05fa0221d88fcf669e0a04903/-1:-1",
        "targetVariableName": "Spacing/2 (8px)",
        "targetVariableSetId": "VariableCollectionId:fc3c86d2404c990c1ac80ea6da19380c4b1f10cc/-1:-1",
        "targetVariableSetName": "_Primitives"
      },
      "com.figma.isOverride": true
    }
  },
  "spacing-lg": {
    "$type": "number",
    "$value": 12,
    "$extensions": {
      "com.figma.variableId": "VariableID:6298:45389",
      "com.figma.scopes": [
        "GAP"
      ],
      "com.figma.aliasData": {
        "targetVariableId": "VariableID:b290c8d8e8964c427f451d459edf6e47b4f18fd1/-1:-1",
        "targetVariableName": "Spacing/3 (12px)",
        "targetVariableSetId": "VariableCollectionId:fc3c86d2404c990c1ac80ea6da19380c4b1f10cc/-1:-1",
        "targetVariableSetName": "_Primitives"
      },
      "com.figma.isOverride": true
    }
  },
  "spacing-xl": {
    "$type": "number",
    "$value": 16,
    "$extensions": {
      "com.figma.variableId": "VariableID:6298:45390",
      "com.figma.scopes": [
        "GAP"
      ],
      "com.figma.aliasData": {
        "targetVariableId": "VariableID:42aff17a843c5dcab0591801782c4189daf178dd/-1:-1",
        "targetVariableName": "Spacing/4 (16px)",
        "targetVariableSetId": "VariableCollectionId:fc3c86d2404c990c1ac80ea6da19380c4b1f10cc/-1:-1",
        "targetVariableSetName": "_Primitives"
      },
      "com.figma.isOverride": true
    }
  },
  "spacing-2xl": {
    "$type": "number",
    "$value": 20,
    "$extensions": {
      "com.figma.variableId": "VariableID:6298:45391",
      "com.figma.scopes": [
        "GAP"
      ],
      "com.figma.aliasData": {
        "targetVariableId": "VariableID:95f1fcb1584d60d1b554d0f4a621b4d4caffaad5/-1:-1",
        "targetVariableName": "Spacing/5 (20px)",
        "targetVariableSetId": "VariableCollectionId:fc3c86d2404c990c1ac80ea6da19380c4b1f10cc/-1:-1",
        "targetVariableSetName": "_Primitives"
      },
      "com.figma.isOverride": true
    }
  },
  "spacing-3xl": {
    "$type": "number",
    "$value": 24,
    "$extensions": {
      "com.figma.variableId": "VariableID:6298:45392",
      "com.figma.scopes": [
        "GAP"
      ],
      "com.figma.aliasData": {
        "targetVariableId": "VariableID:8e1bccd299017890796f5c55ae04321940ec719e/-1:-1",
        "targetVariableName": "Spacing/6 (24px)",
        "targetVariableSetId": "VariableCollectionId:fc3c86d2404c990c1ac80ea6da19380c4b1f10cc/-1:-1",
        "targetVariableSetName": "_Primitives"
      },
      "com.figma.isOverride": true
    }
  },
  "spacing-4xl": {
    "$type": "number",
    "$value": 32,
    "$extensions": {
      "com.figma.variableId": "VariableID:6298:45393",
      "com.figma.scopes": [
        "GAP"
      ],
      "com.figma.aliasData": {
        "targetVariableId": "VariableID:36e424d5d8b56303a33a85943212fa83e609da7b/-1:-1",
        "targetVariableName": "Spacing/8 (32px)",
        "targetVariableSetId": "VariableCollectionId:fc3c86d2404c990c1ac80ea6da19380c4b1f10cc/-1:-1",
        "targetVariableSetName": "_Primitives"
      },
      "com.figma.isOverride": true
    }
  },
  "spacing-5xl": {
    "$type": "number",
    "$value": 40,
    "$extensions": {
      "com.figma.variableId": "VariableID:6433:93631",
      "com.figma.scopes": [
        "GAP"
      ],
      "com.figma.aliasData": {
        "targetVariableId": "VariableID:14243205d323af159c8b8d3e7a6e2f824dfd8695/-1:-1",
        "targetVariableName": "Spacing/10 (40px)",
        "targetVariableSetId": "VariableCollectionId:fc3c86d2404c990c1ac80ea6da19380c4b1f10cc/-1:-1",
        "targetVariableSetName": "_Primitives"
      },
      "com.figma.isOverride": true
    }
  },
  "spacing-6xl": {
    "$type": "number",
    "$value": 48,
    "$extensions": {
      "com.figma.variableId": "VariableID:6298:45394",
      "com.figma.scopes": [
        "GAP"
      ],
      "com.figma.aliasData": {
        "targetVariableId": "VariableID:9ef19eed1866fbf3cfafdd3c6805de465ac5b99d/-1:-1",
        "targetVariableName": "Spacing/12 (48px)",
        "targetVariableSetId": "VariableCollectionId:fc3c86d2404c990c1ac80ea6da19380c4b1f10cc/-1:-1",
        "targetVariableSetName": "_Primitives"
      },
      "com.figma.isOverride": true
    }
  },
  "spacing-7xl": {
    "$type": "number",
    "$value": 64,
    "$extensions": {
      "com.figma.variableId": "VariableID:6298:45395",
      "com.figma.scopes": [
        "GAP"
      ],
      "com.figma.aliasData": {
        "targetVariableId": "VariableID:27c7a98bd13977de9be6cb5126c2e724624e1f41/-1:-1",
        "targetVariableName": "Spacing/16 (64px)",
        "targetVariableSetId": "VariableCollectionId:fc3c86d2404c990c1ac80ea6da19380c4b1f10cc/-1:-1",
        "targetVariableSetName": "_Primitives"
      },
      "com.figma.isOverride": true
    }
  },
  "spacing-8xl": {
    "$type": "number",
    "$value": 80,
    "$extensions": {
      "com.figma.variableId": "VariableID:6298:45396",
      "com.figma.scopes": [
        "GAP"
      ],
      "com.figma.aliasData": {
        "targetVariableId": "VariableID:290eabdcb0302b8a5324294d2ee1a9eb4754e6d6/-1:-1",
        "targetVariableName": "Spacing/20 (80px)",
        "targetVariableSetId": "VariableCollectionId:fc3c86d2404c990c1ac80ea6da19380c4b1f10cc/-1:-1",
        "targetVariableSetName": "_Primitives"
      },
      "com.figma.isOverride": true
    }
  },
  "spacing-9xl": {
    "$type": "number",
    "$value": 96,
    "$extensions": {
      "com.figma.variableId": "VariableID:6298:45397",
      "com.figma.scopes": [
        "GAP"
      ],
      "com.figma.aliasData": {
        "targetVariableId": "VariableID:fa696ca80447c054e609f079fcc14ceeb5bb6b58/-1:-1",
        "targetVariableName": "Spacing/24 (96px)",
        "targetVariableSetId": "VariableCollectionId:fc3c86d2404c990c1ac80ea6da19380c4b1f10cc/-1:-1",
        "targetVariableSetName": "_Primitives"
      },
      "com.figma.isOverride": true
    }
  },
  "spacing-10xl": {
    "$type": "number",
    "$value": 128,
    "$extensions": {
      "com.figma.variableId": "VariableID:6298:45398",
      "com.figma.scopes": [
        "GAP"
      ],
      "com.figma.aliasData": {
        "targetVariableId": "VariableID:97f4019ae63f33c39e5d443f277fcd6ddb587237/-1:-1",
        "targetVariableName": "Spacing/32 (128px)",
        "targetVariableSetId": "VariableCollectionId:fc3c86d2404c990c1ac80ea6da19380c4b1f10cc/-1:-1",
        "targetVariableSetName": "_Primitives"
      },
      "com.figma.isOverride": true
    }
  },
  "spacing-11xl": {
    "$type": "number",
    "$value": 160,
    "$extensions": {
      "com.figma.variableId": "VariableID:6298:45399",
      "com.figma.scopes": [
        "GAP"
      ],
      "com.figma.aliasData": {
        "targetVariableId": "VariableID:e96a9f2cadee0b5ff42b7a9c29b60d85c5f4cf60/-1:-1",
        "targetVariableName": "Spacing/40 (160px)",
        "targetVariableSetId": "VariableCollectionId:fc3c86d2404c990c1ac80ea6da19380c4b1f10cc/-1:-1",
        "targetVariableSetName": "_Primitives"
      },
      "com.figma.isOverride": true
    }
  },
  "$extensions": {
    "com.figma.modeName": "Mode 1"
  }
}